LICENSE.txt
README.md
setup.cfg
setup.py
uacs/__init__.py
uacs/function.py
uacs.egg-info/PKG-INFO
uacs.egg-info/SOURCES.txt
uacs.egg-info/dependency_links.txt
uacs.egg-info/top_level.txt