Metadata-Version: 2.1
Name: uacs
Version: 0.1.1
Summary: This script allows to check services under Linux and sends mails in case of crash of one of them.
Home-page: https://github.com/FLAFLALEBG/Ultimate_Auto_Check_Services
Author: Flavio
Author-email: flaviocomblez@gmail.com
License: GNU General Public License v2 (GPLv2) (GPL-2.0-only)
Platform: UNKNOWN
Classifier: License :: OSI Approved :: MIT License
Classifier: Programming Language :: Python :: 3
